libname/__init__.py
libname/hello.py
hellopkgabc-0.0.1.dist-info/METADATA
hellopkgabc-0.0.1.dist-info/WHEEL
hellopkgabc-0.0.1.dist-info/top_level.txt
hellopkgabc-0.0.1.dist-info/RECORD
